.gitignore
LICENSE
README.md
conftest.py
requirements.txt
setup.cfg
setup.py
data/metrics.csv
data/poisson_testing_df.csv
data/prophet_testing_df.csv
data/wide_format_data.csv
demos/data_creation.ipynb
demos/wrapper_ITS.ipynb
docs/.buildinfo
docs/.nojekyll
docs/BaseITS.html
docs/BaseITS.rst
docs/Makefile
docs/conf.py
docs/developer_guide.html
docs/genindex.html
docs/index.html
docs/index.rst
docs/installation.html
docs/make.bat
docs/modules.html
docs/modules.rst
docs/objects.inv
docs/py-modindex.html
docs/search.html
docs/searchindex.js
docs/_build/doctrees/BaseITS.doctree
docs/_build/doctrees/environment.pickle
docs/_build/doctrees/index.doctree
docs/_build/doctrees/modules.doctree
docs/_build/html/.buildinfo
docs/_build/html/BaseITS.html
docs/_build/html/developer_guide.html
docs/_build/html/genindex.html
docs/_build/html/index.html
docs/_build/html/installation.html
docs/_build/html/modules.html
docs/_build/html/objects.inv
docs/_build/html/py-modindex.html
docs/_build/html/search.html
docs/_build/html/searchindex.js
docs/_build/html/_modules/index.html
docs/_build/html/_modules/BaseITS/custom_transform.html
docs/_build/html/_modules/BaseITS/metrics.html
docs/_build/html/_modules/BaseITS/model_tuning.html
docs/_build/html/_modules/BaseITS/plotting.html
docs/_build/html/_modules/BaseITS/poisson_regression.html
docs/_build/html/_modules/BaseITS/pre_processing.html
docs/_build/html/_modules/BaseITS/prophet_model.html
docs/_build/html/_modules/BaseITS/utils.html
docs/_build/html/_modules/BaseITS/wrapper_class.html
docs/_build/html/_sources/BaseITS.rst.txt
docs/_build/html/_sources/index.rst.txt
docs/_build/html/_sources/modules.rst.txt
docs/_build/html/_static/_sphinx_javascript_frameworks_compat.js
docs/_build/html/_static/basic.css
docs/_build/html/_static/doctools.js
docs/_build/html/_static/documentation_options.js
docs/_build/html/_static/file.png
docs/_build/html/_static/jquery-3.6.0.js
docs/_build/html/_static/jquery.js
src/model_driven_inference_its.egg-info/PKG-INFO
src/model_driven_inference_its.egg-info/SOURCES.txt
src/model_driven_inference_its.egg-info/dependency_links.txt
src/model_driven_inference_its.egg-info/requires.txt
src/model_driven_inference_its.egg-info/top_level.txt
