Metadata-Version: 2.1
Name: model-driven-inference-its
Version: 1.0.3
Summary: Interrupted time series wrapper code based on prophet and Poisson regression
Home-page: https://github.com/IBM/ITS-analysis-for-model-driven-inference
Author: IBM Research Africa
Project-URL: Bug Reports, https://github.com/IBM/ITS-analysis-for-model-driven-inference/issues
Project-URL: Source, https://github.com/IBM/ITS-analysis-for-model-driven-inference/
Keywords: Interrupted Time Series,Time Series,Policy Makers
Classifier: Development Status :: 4 - Beta
Classifier: Intended Audience :: Science/Research
Classifier: Intended Audience :: Developers
Classifier: License :: OSI Approved :: Apache Software License
Classifier: Operating System :: OS Independent
Classifier: Topic :: Documentation :: Sphinx
Classifier: Topic :: Scientific/Engineering :: Visualization
Classifier: Topic :: Scientific/Engineering :: Artificial Intelligence
Classifier: Programming Language :: Python :: 3.9
Requires-Python: >=3.9
Provides-Extra: test
License-File: LICENSE
